[
    {
        "subcat_id": "abc",
        "product_name": "T-shirt",
        "description": "Long Sleeve T-shirt",
        "price": "500",
        "image": "path"
    },
    {
        "subcat_id": "abc",
        "product_name": "Jeans",
        "description": "Belbottom Jeans",
        "price": "500",
        "image": "path"
    },
    {
        "subcat_id": "abc",
        "product_name": "Crop Top",
        "description": "Printed Crop Top",
        "price": "500",
        "image": "path"
    },
    {
        "subcat_id": "abc",
        "product_name": "Leggings",
        "description": "Printed Leggings",
        "price": "500",
        "image": "path"
    }
]